{
  "page": {
    "type": "70X50"
  },
  "blocks": [
    {
      "text": "打印:{{当前时间_年月日}}",
      "style": {
        "position": "absolute",
        "left": "8px",
        "top": "8px",
        "fontSize": "12px"
      }
    },
    {
      "type": "qrcode",
      "qrcode": "{{溯源码}}",
      "style": {
        "position": "absolute",
        "left": "184px",
        "top": "97px",
        "width": "70px",
        "height": "70px",
        "right": ""
      }
    },
    {
      "text": "地址:{{商户地址}}",
      "style": {
        "position": "absolute",
        "left": "8px",
        "top": "25px"
      }
    },
    {
      "text": "客服:{{客服电话}}",
      "style": {
        "position": "absolute",
        "left": "",
        "top": "8px",
        "right": "8px",
        "fontSize": "12px"
      }
    },
    {
      "text": "司机:{{司机}}",
      "style": {
        "position": "absolute",
        "left": "9px",
        "top": "41px"
      }
    },
    {
      "text": "{{SKU}}",
      "style": {
        "position": "absolute",
        "left": "8px",
        "top": "60px",
        "fontWeight": "bold",
        "fontSize": "16px"
      }
    },
    {
      "type": "line",
      "style": {
        "position": "absolute",
        "left": "0px",
        "top": "23px",
        "borderTopColor": "black",
        "borderTopWidth": "1px",
        "borderTopStyle": "solid",
        "width": "100%"
      }
    },
    {
      "type": "line",
      "style": {
        "position": "absolute",
        "left": "0px",
        "top": "58px",
        "borderTopColor": "black",
        "borderTopWidth": "1px",
        "borderTopStyle": "solid",
        "width": "100%"
      }
    },
    {
      "text": "下单:{{下单}}",
      "style": {
        "position": "absolute",
        "left": "8px",
        "top": "97px"
      }
    },
    {
      "text": "实称:{{实称}}",
      "style": {
        "position": "absolute",
        "left": "8px",
        "top": "113px"
      }
    },
    {
      "text": "溯源码:{{溯源码}}",
      "style": {
        "position": "absolute",
        "left": "",
        "top": "168px",
        "fontSize": "12px",
        "right": "8px"
      }
    },
    {
      "text": "备注:{{备注}}",
      "style": {
        "position": "absolute",
        "left": "8px",
        "top": "130px",
        "right": "78px"
      }
    }
  ]
}